setup.py
begen/__init__.py
begen.egg-info/PKG-INFO
begen.egg-info/SOURCES.txt
begen.egg-info/dependency_links.txt
begen.egg-info/not-zip-safe
begen.egg-info/top_level.txt