Metadata-Version: 1.0
Name: begen
Version: 0.3
Summary: versatile http/https traffic generator
Home-page: https://github.com/perrin-ay/begen
Author: perrin-ay
Author-email: arnabchat@hotmail.com
License: UNKNOWN
Platform: UNKNOWN
